js/typeahead/__init__.py
js/typeahead/resources/js/bloodhound.js
js/typeahead/resources/js/bloodhound.min.js
js/typeahead/resources/js/typeahead.bundle.js
js/typeahead/resources/js/typeahead.bundle.min.js
js/typeahead/resources/js/typeahead.jquery.js
js/typeahead/resources/js/typeahead.jquery.min.js
js.typeahead-0.11.1.dist-info/entry_points.txt
js.typeahead-0.11.1.dist-info/WHEEL
js.typeahead-0.11.1.dist-info/METADATA
js.typeahead-0.11.1.dist-info/RECORD
